README.md
setup.py
src/pitchbase/__init__.py
src/pitchbase/auth.py
src/pitchbase/client.py
src/pitchbase/commands.py
src/pitchbase/config.py
src/pitchbase/constants.py
src/pitchbase/logger.py
src/pitchbase/util.py
src/pitchbase.egg-info/PKG-INFO
src/pitchbase.egg-info/SOURCES.txt
src/pitchbase.egg-info/dependency_links.txt
src/pitchbase.egg-info/entry_points.txt
src/pitchbase.egg-info/not-zip-safe
src/pitchbase.egg-info/requires.txt
src/pitchbase.egg-info/top_level.txt
tests/test_util.py