Metadata-Version: 2.1
Name: pitchbase
Version: 0.13.2
Summary: Command Line utility for pitchbase.
Home-page: https://github.dena.jp/AI/pitchbase
Author: Hiroshi Toyama
Author-email: toyama0919@gmail.com
License: MIT
Keywords: pitchbase tool aws
Classifier: Programming Language :: Python :: 3.6
Classifier: Programming Language :: Python :: 3.7
Classifier: Programming Language :: Python :: 3.8
Classifier: Programming Language :: Python :: 3.9
Provides-Extra: test
